json_serde/__init__.py
json_serde/_utils.py
json_serde/serde.py
json_serde-0.0.11.dist-info/LICENSE-APACHE
json_serde-0.0.11.dist-info/LICENSE-MIT
json_serde-0.0.11.dist-info/METADATA
json_serde-0.0.11.dist-info/WHEEL
json_serde-0.0.11.dist-info/top_level.txt
json_serde-0.0.11.dist-info/RECORD
